protobuf/__init__.py
python/__init__.py
botdata_sdk-1.0.0.dist-info/METADATA
botdata_sdk-1.0.0.dist-info/WHEEL
botdata_sdk-1.0.0.dist-info/top_level.txt
botdata_sdk-1.0.0.dist-info/RECORD
