Metadata-Version: 2.1
Name: botdata-sdk
Version: 1.0.0
Summary: Botdata SDK
Author-email: Martin Hu <martin.hu.720@bot.auto>, Yinan Zhang <yinan.zhang.481@bot.auto>
Project-URL: Repo, https://github.com/bot-auto/botdata-sdk
Classifier: Development Status :: 3 - Alpha
Classifier: Programming Language :: Python :: 3
Classifier: Programming Language :: Python :: 3.10
Classifier: Programming Language :: Python :: 3.11
Classifier: Programming Language :: Python :: 3 :: Only
Requires-Python: >=3.10
Provides-Extra: dev
Requires-Dist: check-manifest ; extra == 'dev'
Provides-Extra: test
Requires-Dist: coverage ; extra == 'test'
